py2700/MeasurementType.py
py2700/Multimeter.py
py2700/__init__.py
py2700-0.1.0.dist-info/LICENSE
py2700-0.1.0.dist-info/METADATA
py2700-0.1.0.dist-info/WHEEL
py2700-0.1.0.dist-info/top_level.txt
py2700-0.1.0.dist-info/RECORD
