Metadata-Version: 2.1
Name: py2700
Version: 0.1.0
Summary: A Python package to interface with a Keithley 2700 multimeter
Home-page: https://github.com/ngpaladi/py2700
Author: ngpaladi
Author-email: py2700@noahpaladino.com
License: UNKNOWN
Platform: UNKNOWN
Classifier: Programming Language :: Python :: 3
Classifier: License :: OSI Approved :: Apache Software License
Classifier: Operating System :: OS Independent
Requires-Dist: PyVISA
Requires-Dist: PyVISA-py
